code/Common.py
code/CrackCode.py
code/Download.py
code/ExtractFile.py
code/Image.py
code/Loger.py
code/Mysql.py
code/Subtitles.py
code/Time.py
code/Translation.py
code/UncompressRAR.py
code/_SSH.py
code/__init__.py
code/ownEmail.py
owntools/Common.py
owntools/CrackCode.py
owntools/Download.py
owntools/ExtractFile.py
owntools/Image.py
owntools/Loger.py
owntools/Mysql.py
owntools/Ssh.py
owntools/Subtitles.py
owntools/Time.py
owntools/Translation.py
owntools/UncompressRAR.py
owntools/_SSH.py
owntools/__init__.py
owntools/ownEmail.py
src/Common.py
src/CrackCode.py
src/Download.py
src/ExtractFile.py
src/Image.py
src/Loger.py
src/Mysql.py
src/Subtitles.py
src/Time.py
src/Translation.py
src/UncompressRAR.py
src/_SSH.py
src/__init__.py
src/ownEmail.py
owntools-2.0.dist-info/METADATA
owntools-2.0.dist-info/WHEEL
owntools-2.0.dist-info/top_level.txt
owntools-2.0.dist-info/RECORD
