Metadata-Version: 2.1
Name: owntools
Version: 2.0
Summary: Tools for myself
Home-page: https://github.com/liangxiuyu/owntools
Author: Neely
Author-email: liangxiuyu@outlook.com
Classifier: Programming Language :: Python :: 3
Classifier: License :: OSI Approved :: MIT License
